CHANGES.txt
CONTRIBUTORS.txt
LICENSE.txt
MANIFEST.in
README.rst
setup.cfg
setup.py
Blogofile.egg-info/PKG-INFO
Blogofile.egg-info/SOURCES.txt
Blogofile.egg-info/dependency_links.txt
Blogofile.egg-info/entry_points.txt
Blogofile.egg-info/not-zip-safe
Blogofile.egg-info/pbr.json
Blogofile.egg-info/requires.txt
Blogofile.egg-info/top_level.txt
blogofile/__init__.py
blogofile/cache.py
blogofile/config.py
blogofile/controller.py
blogofile/default_config.py
blogofile/exception.py
blogofile/filter.py
blogofile/main.py
blogofile/plugin.py
blogofile/server.py
blogofile/template.py
blogofile/util.py
blogofile/writer.py
converters/blogger2blogofile.py
converters/wordpress2blogofile.py
requirements/develop.txt
requirements/production.txt