Metadata-Version: 1.1
Name: Blogofile
Version: 0.8.3
Summary: A static website compiler and blog engine
Home-page: http://www.blogofile.com
Author: Ryan McGuire, Doug Latornell, and the Blogofile Contributors
Author-email: blogofile-discuss@googlegroups.com
License: MIT
Platform: UNKNOWN
Classifier: Programming Language :: Python :: 2
Classifier: Programming Language :: Python :: 2.6
Classifier: Programming Language :: Python :: 2.7
Classifier: Programming Language :: Python :: 3
Classifier: Programming Language :: Python :: 3.2
Classifier: Development Status :: 4 - Beta
Classifier: License :: OSI Approved :: MIT License
Classifier: Programming Language :: Python :: Implementation :: CPython
Classifier: Environment :: Console
Classifier: Natural Language :: English
